[{"__symbolic":"module","version":3,"metadata":{"OpenUrlModalModule":{"__symbolic":"class","decorators":[{"__symbolic":"call","expression":{"__symbolic":"reference","module":"@angular/core","name":"NgModule"},"arguments":[{"imports":[{"__symbolic":"reference","module":"ionic-angular","name":"IonicModule"}],"declarations":[{"__symbolic":"reference","module":"./open-url-modal-component","name":"OpenUrlModalCmp"}],"exports":[{"__symbolic":"reference","module":"./open-url-modal-component","name":"OpenUrlModalCmp"}],"entryComponents":[{"__symbolic":"reference","module":"./open-url-modal-component","name":"OpenUrlModalCmp"}]}]}],"statics":{"forRoot":{"__symbolic":"function","parameters":[],"value":{"ngModule":{"__symbolic":"reference","name":"OpenUrlModalModule"},"providers":[{"__symbolic":"reference","module":"./open-url-modal","name":"OpenUrlModalController"}]}}}}},"exports":[{"from":"./open-url-modal","export":["OpenUrlModalController"]}]},{"__symbolic":"module","version":1,"metadata":{"OpenUrlModalModule":{"__symbolic":"class","decorators":[{"__symbolic":"call","expression":{"__symbolic":"reference","module":"@angular/core","name":"NgModule"},"arguments":[{"imports":[{"__symbolic":"reference","module":"ionic-angular","name":"IonicModule"}],"declarations":[{"__symbolic":"reference","module":"./open-url-modal-component","name":"OpenUrlModalCmp"}],"exports":[{"__symbolic":"reference","module":"./open-url-modal-component","name":"OpenUrlModalCmp"}],"entryComponents":[{"__symbolic":"reference","module":"./open-url-modal-component","name":"OpenUrlModalCmp"}]}]}],"statics":{"forRoot":{"__symbolic":"function","parameters":[],"value":{"ngModule":{"__symbolic":"reference","name":"OpenUrlModalModule"},"providers":[{"__symbolic":"reference","module":"./open-url-modal","name":"OpenUrlModalController"}]}}}}},"exports":[{"from":"./open-url-modal","export":["OpenUrlModalController"]}]}]